livetube/__init__.py
livetube/__main__.py
livetube/communityPosts.py
livetube/memberShips.py
livetube/membership_pb2.py
livetube/playerResponse.py
livetube/studio_pb2.py
livetube/utils.py
livetube/util/__init__.py
livetube/util/cache.py
livetube/util/cipher.py
livetube/util/exceptions.py
livetube/util/js.py
livetube/util/parser.py
livetube/util/player.py
livetube/util/regex.py
livetube-2.2.10.dist-info/LICENSE
livetube-2.2.10.dist-info/METADATA
livetube-2.2.10.dist-info/WHEEL
livetube-2.2.10.dist-info/top_level.txt
livetube-2.2.10.dist-info/RECORD
